ocrd_pagetopdf/PageToPdf.jar
ocrd_pagetopdf/__init__.py
ocrd_pagetopdf/alto_processor.py
ocrd_pagetopdf/cli.py
ocrd_pagetopdf/copyright.txt
ocrd_pagetopdf/multipagepdf.py
ocrd_pagetopdf/ocrd-tool.json
ocrd_pagetopdf/page_processor.py
ocrd_pagetopdf/data/AletheiaSans.ttf
ocrd_pagetopdf/lib/PrimaBasic.jar
ocrd_pagetopdf/lib/PrimaDla.jar
ocrd_pagetopdf/lib/PrimaIo.jar
ocrd_pagetopdf/lib/PrimaMaths.jar
ocrd_pagetopdf/lib/PrimaText.jar
ocrd_pagetopdf/lib/itextpdf-5.5.2.jar
ocrd_pagetopdf-2.0.1.dist-info/licenses/LICENSE
ocrd_pagetopdf-2.0.1.dist-info/METADATA
ocrd_pagetopdf-2.0.1.dist-info/WHEEL
ocrd_pagetopdf-2.0.1.dist-info/entry_points.txt
ocrd_pagetopdf-2.0.1.dist-info/top_level.txt
ocrd_pagetopdf-2.0.1.dist-info/RECORD
