Metadata-Version: 2.4
Name: ocrd_pagetopdf
Version: 2.0.1
Summary: OCR-D wrapper for prima-pagetopdf
Author-email: Jan Kamlah <jan.kamlah@uni-mannheim.de>, Robert Sachunsky <robert.sachunsky@slub-dresden.de>
License:                                  Apache License
Project-URL: Homepage, https://github.com/OCR-D/ocrd_pagetopdf
Project-URL: Repository, https://github.com/OCR-D/ocrd_pagetopdf.git
Keywords: ocr,ocr-d,page-xml
Classifier: Development Status :: 5 - Production/Stable
Classifier: Environment :: Console
Classifier: Intended Audience :: Science/Research
Classifier: Intended Audience :: Other Audience
Classifier: License :: OSI Approved :: GNU General Public License v3 (GPLv3)
Classifier: Programming Language :: Python :: 3
Classifier: Programming Language :: Python :: 3 :: Only
Classifier: Topic :: Text Processing
Requires-Python: >=3.8
License-File: LICENSE
Requires-Dist: ocrd>=3.0.4
Requires-Dist: scipy
Dynamic: license-file
